gittidy/__init__.py
gittidy/exception.py
gittidy/git.py
gittidy-0.3.1.dist-info/METADATA
gittidy-0.3.1.dist-info/WHEEL
gittidy-0.3.1.dist-info/top_level.txt
gittidy-0.3.1.dist-info/RECORD
