Metadata-Version: 2.4
Name: GitTidy
Version: 0.3.1
Requires-Python: >=3.10
Requires-Dist: LoggerMan<0.2,>=0.1
Requires-Dist: PyShellMan<0.2,>=0.1
Requires-Dist: MDit<0.2,>=0.1
Requires-Dist: ExceptionMan<0.2,>=0.1
